dreamai/__init__.py
dreamai/agent.py
dreamai/history_processors.py
dreamai/py.typed
dreamai/test_run_context.py
dreamai/.logfire/.gitignore
dreamai/.logfire/logfire_credentials.json
dreamai-4.2.13.dist-info/METADATA
dreamai-4.2.13.dist-info/WHEEL
dreamai-4.2.13.dist-info/RECORD
