Metadata-Version: 2.4
Name: dreamai
Version: 4.2.13
Summary: Add your description here
Author-email: HamzaFarhan <thehamza96@gmail.com>
Requires-Python: >=3.13
Requires-Dist: docstring-parser>=0.16
Requires-Dist: formulas>=1.2.11
Requires-Dist: gradio>=5.42.0
Requires-Dist: httpx>=0.28.1
Requires-Dist: ipykernel>=6.29.5
Requires-Dist: logfire[httpx]>=3.24.2
Requires-Dist: loguru>=0.7.3
Requires-Dist: matplotlib>=3.10.5
Requires-Dist: openpyxl>=3.1.5
Requires-Dist: pandas>=2.3.1
Requires-Dist: polars>=1.32.2
Requires-Dist: pydantic-ai>=0.7.0
Requires-Dist: pytest>=8.4.1
Requires-Dist: python-dotenv>=1.1.1
Requires-Dist: watchdog>=6.0.0
Requires-Dist: xlwings>=0.33.15
